aioexec/__init__.py
aioexec-0.5.1.dist-info/LICENSE
aioexec-0.5.1.dist-info/METADATA
aioexec-0.5.1.dist-info/WHEEL
aioexec-0.5.1.dist-info/RECORD
